Workbook
Name ADDONS_TOTAL: 'Add-Ons'!$G$17
Name CONTINGENCY_PCT: Assumptions!$C$9
Name DEC_B1: Decisions!$E$6
Name DEC_B2: Decisions!$E$7
Name DEC_B5: Decisions!$E$8
Name INCLUDE_CONTINGENCY: Assumptions!$C$10
Name MGMT_MONTHLY: 'Management Tiers'!$E$10
Name SETUP_FEE: Setup!$C$17
Name STAGE_B_MONTHS: Assumptions!$C$8
Name VAT_BASIS: Decisions!$D$9
Name VAT_RATE: Assumptions!$C$5

Sheet Cover
B2: PropFlo Marketing Budget — Marketing & Ad Spend Only
B4: Prepared by | C4: Interon
B5: Client | C5: PropFlo / Newco (legal entity TBC)
B6: Scope | C6: Marketing services (Interon fees) + media spend (paid to Google, Meta, LinkedIn). Everything else is excluded.
B7: Status | C7: Working draft — not yet approved
B8: Version | C8: v2.0 (2026-07-06)
B9: VAT policy | C9: All figures ex VAT unless the VAT toggle on Summary is used. VAT bases are never mixed.
B10: Currency | C10: ZAR
B12: How to use this workbook
B13: 1 | C13: Yellow cells are inputs — edit these.
B14: 2 | C14: Grey cells are calculated — do not edit; edit the source input instead.
B15: 3 | C15: Green cells are totals or selected-scenario headlines.
B16: 4 | C16: The Decisions sheet drives the Selected Scenario column on Summary. Change a dropdown, and Summary recalculates.
B17: 5 | C17: Low / Mid / High columns on Summary are fixed reference scenarios.
B18: 6 | C18: The far-right column on every sheet explains each item in plain English for non-marketing readers.
B20: Sheets
B21: Summary | C21: Low / Mid / High + Selected Scenario. Programme totals ex and incl VAT.
B22: Decisions | C22: Four dropdowns: landing page choice, when management fee starts, ad-spend phasing, VAT basis.
B23: Assumptions | C23: VAT rate, contingency %, Stage A weeks, Stage B months.
B24: Setup | C24: One-off preparation fee — line items that add up to the R55,000 package.
B25: Landing Pages | C25: One-off cost to build the web page(s) adverts send people to.
B26: Management Tiers | C26: Three monthly management options. Select the active tier.
B27: 90-Day Plan | C27: Month-by-month build of Stage B (the live campaign).
B28: Ad Spend | C28: Media spend paid to Google / Meta / LinkedIn — not paid to Interon.
B29: Add-Ons | C29: Optional extras with Yes/No toggles.

Sheet Summary
B2: Summary — Marketing & Ad Spend (ex VAT unless noted)
B3: Low / Mid / High are fixed reference scenarios. Selected Scenario recalculates from the Decisions sheet.
B5: Line | C5: Low (R) | D5: Mid (R) | E5: High (R) | F5: Selected Scenario (R) | G5: Plain English (what this is for)
B6: Setup fee (once-off) | C6: 55000 | D6: 55000 | E6: 55000 | F6: =SETUP_FEE | G6: One-off cost to prepare everything before the first advert runs — plans, compliance, tracking, campaign builds, ad copy.
B7: Landing pages (once-off) | C7: 10000 | D7: 35000 | E7: 65000 | F7: =DEC_B1 | G7: One-off cost to build the web page(s) Google Ads sends people to.
B8: Stage A management (prep add-on) | C8: 0 | D8: 0 | E8: 0 | F8: =DEC_B2 | G8: Optional monthly fee during the preparation stage, before adverts are live. Normally R0.
B9: Stage B management (90 days) | C9: 54000 | D9: 96000 | E9: 165000 | F9: =MGMT_MONTHLY*STAGE_B_MONTHS | G9: Interon's monthly fee while adverts are live, covering optimisation, testing, and reporting. Three months.
B10: Ad spend (paid to platforms) | C10: 60000 | D10: 97500 | E10: 180000 | F10: =DEC_B5 | G10: Money paid directly to Google, Facebook, and LinkedIn. Not paid to Interon.
B11: Optional add-ons | C11: 0 | D11: 0 | E11: 0 | F11: =ADDONS_TOTAL | G11: Anything switched to Yes on the Add-Ons sheet.
B12: Contingency (Interon fees only) | C12: 0 | D12: 0 | E12: 0 | F12: =IF(INCLUDE_CONTINGENCY="Yes",(F6+F7+F8+F9)*CONTINGENCY_PCT,0) | G12: A 10% safety buffer on Interon fees for approved scope changes. Off by default.
B13: Programme total ex VAT | C13: =SUM(C6:C12) | D13: =SUM(D6:D12) | E13: =SUM(E6:E12) | F13: =SUM(F6:F12) | G13: The full 90-day marketing investment before VAT.
B14: VAT @ 15% | C14: =C13*VAT_RATE | D14: =D13*VAT_RATE | E14: =E13*VAT_RATE | F14: =F13*VAT_RATE | G14: South African VAT applied to the programme total.
B15: Programme total incl VAT | C15: =C13+C14 | D15: =D13+D14 | E15: =E13+E14 | F15: =F13+F14 | G15: The full amount payable, VAT included.
B17: Splits
B18: Split | C18: Low (R) | D18: Mid (R) | E18: High (R) | F18: Selected (R) | G18: Plain English (what this is for)
B19: Interon fees ex VAT | C19: =C6+C7+C8+C9+C11+C12 | D19: =D6+D7+D8+D9+D11+D12 | E19: =E6+E7+E8+E9+E11+E12 | F19: =F6+F7+F8+F9+F11+F12 | G19: What Interon is paid: setup + landing pages + management + add-ons + contingency.
B20: Ad spend (client → platforms) | C20: =C10 | D20: =D10 | E20: =E10 | F20: =F10 | G20: What PropFlo pays directly to Google, Facebook, and LinkedIn.

Sheet Decisions
B2: Commercial Decisions — Selected Scenario Inputs
B3: Change the yellow dropdown in the Selection column. Grey cells show the resolved R value used by Summary.
H4: Lookup values (editable)
B5: Ref | C5: Decision | D5: Selection | E5: Resolved (R) | F5: Plain English (what this is for)
B6: B1 | C6: Which landing page option? | D6: Interim page (R10,000) | E6: =VLOOKUP(D6,$H$6:$I$9,2,FALSE) | F6: The web page(s) Google Ads sends people to. Bigger = more pages for different audiences, better conversion. Interim = single quick page to get started. | H6: Interim page (R10,000) | I6: 10000
B7: B2 | C7: When does the monthly management fee start? | D7: At launch (Day 0) | E7: =VLOOKUP(D7,$H$10:$I$12,2,FALSE) | F7: The monthly Interon fee only makes sense once adverts are live. Options: no charge during prep (recommended), a small prep-coordination fee, or full fee from kick-off. | H7: Basic (R15,500) | I7: 15500
B8: B5 | C8: Ad-spend phasing across the 90-day live campaign | D8: Phased (25/30/40) | E8: =VLOOKUP(D8,$H$13:$I$15,2,FALSE) | F8: How much is paid to Google / Meta / LinkedIn each month. Phased = start small, grow with evidence. Flat = same every month. Custom = set your own numbers on Ad Spend sheet. | H8: Conversion set (R35,000) | I8: 35000
B9: B6 | C9: VAT basis for the client-facing headline number | D9: Ex VAT (VAT shown separately) | E9: Presentation only | F9: How the total is shown to the client. Ex VAT is the norm for B2B in South Africa. Incl VAT shows the full amount payable. | H9: Full site (R65,000) | I9: 65000
H10: At launch (Day 0) | I10: 0
H11: Prep-coordination fee | I11: 12000
H12: Full from kick-off | I12: 80000
H13: Phased (25/30/40) | I13: 95000
H14: Flat R32k | I14: 96000
H15: Custom | I15: ='Ad Spend'!$F$8
H16: Ex VAT (VAT shown separately)
H17: Incl VAT

Sheet Assumptions
B2: Assumptions
B4: Assumption | C4: Value | D4: Plain English (what this is for)
B5: VAT rate | C5: 0.15 | D5: South African VAT. Change here to update the incl-VAT line on Summary.
B6: Currency | C6: ZAR | D6: All figures in South African Rand.
B7: Stage A duration (weeks) | C7: 10 | D7: Preparation stage — the weeks before any advert goes live. Used to plan, build, test, and get approvals.
B8: Stage B duration (months) | C8: 3 | D8: Live campaign duration — the 90-day period when adverts are running and money is being spent on media.
B9: Contingency (% of Interon fees) | C9: 0.1 | D9: A safety buffer added on top of Interon fees to cover approved scope changes. Applied to setup + management only.
B10: Include contingency in totals? | C10: No | D10: Switch to Yes to add the contingency line to Summary totals.

Sheet Setup
B2: Setup Fee — Line-Item Build (once-off, ex VAT)
B3: The R55,000 setup fee is a discounted package. Line items are indicative allocations; the package price is the commercial figure.
B5: Line item | C5: Ex VAT | D5: Plain English (what this is for)
B6: Discovery, strategy and planning | C6: 8500 | D6: Time spent understanding the business, deciding who the marketing targets, and setting the 90-day plan.
B7: Compliance questions and claims preparation | C7: 6500 | D7: Working out what PropFlo is legally allowed to say in adverts and on the website. Finance is regulated in South Africa.
B8: Competitor and keyword research | C8: 6500 | D8: Studying what other bridging-finance companies do, and finding the exact words people type into Google when they need this service.
B9: Funnel and landing page planning | C9: 7500 | D9: Designing the path a person takes from Google click → website → enquiry form → sales team, and deciding what each page needs to say.
B10: Tracking and reporting structure | C10: 7500 | D10: Setting up Google Analytics, Google Ads conversion tracking, and tags so we can see which adverts produce enquiries — and which produce funded deals.
B11: Google Ads campaign setup | C11: 7500 | D11: Building the Google Ads account: search campaigns, ad groups, keywords, adverts, and bid strategy.
B12: Meta retargeting setup | C12: 4500 | D12: Building Facebook and Instagram adverts that follow up with people who visited the website but did not enquire.
B13: LinkedIn partner campaign setup | C13: 4500 | D13: Setting up LinkedIn to reach estate agents and conveyancers who can refer sellers to PropFlo.
B14: Initial copy and creative direction | C14: 6500 | D14: Writing the first version of the words, headlines, and visual style used across adverts, landing pages, and follow-up messages.
B15: Partner outreach framework | C15: 2000 | D15: Preparing the material used to introduce PropFlo to estate agents and conveyancers as a referral partner.
B16: Line-item total (undiscounted) | C16: =SUM(C6:C15) | D16: What the setup would cost if each line was quoted separately. Sums to R61,500.
B17: Packaged setup fee (discounted) | C17: 55000 | D17: The single once-off setup fee — a discounted package covering everything above.

Sheet Landing Pages
B2: Landing Page Options (once-off, ex VAT)
B3: The "landing page" is the web page adverts send people to. The right choice depends on how many audiences we need to serve at launch.
B5: Option | C5: Low (R) | D5: High (R) | E5: Selected (R) | F5: Plain English (what this is for)
B6: Interim page | C6: 8000 | D6: 15000 | E6: 10000 | F6: A single quick page to get started while a bigger website is being built separately. Keeps the launch on schedule.
B7: Basic landing page | C7: 12500 | D7: 18500 | E7: 15500 | F7: One dedicated page for property sellers to land on from Google ads and submit an enquiry. Just enough to test the funnel.
B8: Conversion landing page set | C8: 25000 | D8: 45000 | E8: 35000 | F8: A small group of pages: seller page, partner-referral page, FAQ, and thank-you page. Handles the different audiences properly. Recommended.
B9: Full website improvement | C9: 45000 | D9: 85000 | E9: 65000 | F9: A broader website refresh with better structure, mobile experience, and tracking. Bigger investment, longer to build.
B11: Decision B1 currently resolves to:
B12: Landing pages (Selected Scenario) | C12: =DEC_B1 | F12: Change the selection on the Decisions sheet.

Sheet Management Tiers
B2: Monthly Management Tiers (ex VAT)
B3: Three tiers of ongoing agency support while adverts are live. Select the active tier at the bottom — it feeds Summary.
B5: Tier | C5: Monthly (R) | D5: 3-month total (R) | E5: Plain English (what this is for)
B6: Controlled Launch | C6: 18000 | D6: =C6*STAGE_B_MONTHS | E6: The minimum agency support to keep Google Ads running and produce a monthly report. Suits a small, cautious first launch.
B7: Growth Management | C7: 32000 | D7: =C7*STAGE_B_MONTHS | E7: Google Ads plus Facebook retargeting, landing-page tweaks, monthly reporting, strategy call, and campaign testing. The recommended default.
B8: Full Agency Management | C8: 55000 | D8: =C8*STAGE_B_MONTHS | E8: Everything in Growth plus LinkedIn, SEO content coordination, email/WhatsApp follow-ups, and a quarterly review. For aggressive growth.
B10: Selected tier | C10: Growth Management | D10: Monthly rate → | E10: =VLOOKUP(C10,B6:C8,2,FALSE)
B11: Stage B total (3 months) | E11: =MGMT_MONTHLY*STAGE_B_MONTHS

Sheet 90-Day Plan
B2: Stage B — 90-Day Live Campaign Build (ex VAT)
B3: Month-by-month cash view of the live campaign. Uses the resolved decisions and the selected management tier.
B5: Line | C5: Month 1 | D5: Month 2 | E5: Month 3 | F5: 90-day total | G5: Plain English (what this is for)
B6: Setup (once-off) | C6: =SETUP_FEE | D6: 0 | E6: 0 | F6: =SUM(C6:E6) | G6: Billed on kick-off. Covers the preparation work before adverts go live.
B7: Landing pages (once-off) | C7: =DEC_B1 | D7: 0 | E7: 0 | F7: =SUM(C7:E7) | G7: Builds the web page(s) Google Ads sends people to.
B8: Monthly management | C8: =MGMT_MONTHLY | D8: =MGMT_MONTHLY | E8: =MGMT_MONTHLY | F8: =SUM(C8:E8) | G8: Interon's monthly fee to run, optimise, and report on the campaigns.
B9: Ad spend (to platforms) | C9: ='Ad Spend'!$C$12 | D9: ='Ad Spend'!$D$12 | E9: ='Ad Spend'!$E$12 | F9: =DEC_B5 | G9: Money paid directly by PropFlo to Google, Facebook, and LinkedIn. Not an Interon fee.
B10: Stage A management (if any) | C10: =DEC_B2 | D10: 0 | E10: 0 | F10: =SUM(C10:E10) | G10: Only non-zero if Decision B2 is not "At launch". Optional prep-period fee.
B11: Monthly total (ex VAT) | C11: =SUM(C6:C10) | D11: =SUM(D6:D10) | E11: =SUM(E6:E10) | F11: =SUM(F6:F10) | G11: Selected Scenario 90-day total investment.

Sheet Ad Spend
B2: Ad Spend Phasing (ex VAT, paid to platforms)
B3: Three phasing options. The Selected row below feeds the 90-Day Plan and the Summary.
B5: Option | C5: Month 1 | D5: Month 2 | E5: Month 3 | F5: 90-day total | G5: Plain English (what this is for)
B6: Phased (25/30/40) | C6: 25000 | D6: 30000 | E6: 40000 | F6: =SUM(C6:E6) | G6: Start small to test which adverts, keywords, and audiences actually produce enquiries. Increase spend only on the winners. Lowers wasted spend in Month 1.
B7: Flat R32k | C7: 32000 | D7: 32000 | E7: 32000 | F7: =SUM(C7:E7) | G7: Same amount every month. Easier for the finance team to budget, but less efficient — you spend the full amount before knowing what works.
B8: Custom | C8: 25000 | D8: 30000 | E8: 40000 | F8: =SUM(C8:E8) | G8: Set your own monthly amounts. The total here is what feeds Decision B5 when "Custom" is chosen.
B10: Selected phasing (from Decision B5)
B11: Selection | C11: Month 1 | D11: Month 2 | E11: Month 3 | F11: 90-day total | G11: Plain English (what this is for)
B12: Resolved M1/M2/M3 | C12: =IF(Decisions!$D$8="Phased (25/30/40)",C6,IF(Decisions!$D$8="Flat R32k",C7,C8)) | D12: =IF(Decisions!$D$8="Phased (25/30/40)",D6,IF(Decisions!$D$8="Flat R32k",D7,D8)) | E12: =IF(Decisions!$D$8="Phased (25/30/40)",E6,IF(Decisions!$D$8="Flat R32k",E7,E8)) | F12: =SUM(C12:E12) | G12: The active monthly ad spend used by the 90-Day Plan and Summary.

Sheet Add-Ons
B2: Optional Add-Ons (ex VAT)
B3: Toggle Include = YES to add the mid value to the Selected Scenario total on Summary. Ranges are indicative.
B5: Add-on | C5: Low (R) | D5: High (R) | E5: Mid (R) | F5: Include? | G5: Cost added (R) | H5: Plain English (what this is for)
B6: Additional landing page | C6: 7500 | D6: 15000 | E6: 11250 | F6: No | G6: =IF(F6="Yes",E6,0) | H6: One extra landing page for a specific audience or campaign (e.g. estate agents, a promotion).
B7: Blog article | C7: 1500 | D7: 3500 | E7: 2500 | F7: No | G7: =IF(F7="Yes",E7,0) | H7: One SEO-friendly article that helps PropFlo rank on Google over time. Cost per article.
B8: SEO content cluster | C8: 8500 | D8: 18500 | E8: 13500 | F8: No | G8: =IF(F8="Yes",E8,0) | H8: A group of related articles built to support each other in Google search results.
B9: Extra ad creative set | C9: 3500 | D9: 8500 | E9: 6000 | F9: No | G9: =IF(F9="Yes",E9,0) | H9: New images/videos for adverts so they don't "wear out" with the audience. Refreshed regularly.
B10: Email nurture sequence | C10: 4500 | D10: 9500 | E10: 7000 | F10: No | G10: =IF(F10="Yes",E10,0) | H10: A set of automatic emails sent to enquirers over days/weeks to keep PropFlo top of mind.
B11: WhatsApp script pack | C11: 2500 | D11: 6500 | E11: 4500 | F11: No | G11: =IF(F11="Yes",E11,0) | H11: Pre-written WhatsApp messages the sales team can send at each stage of the lead process.
B12: Partner brochure | C12: 4500 | D12: 9500 | E12: 7000 | F12: No | G12: =IF(F12="Yes",E12,0) | H12: A printable/PDF brochure used to introduce PropFlo to estate agents and conveyancers.
B13: Monthly SEO content management | C13: 8500 | D13: 18500 | E13: 13500 | F13: No | G13: =IF(F13="Yes",E13,0) | H13: Ongoing article writing and SEO work each month. Recurring, not once-off.
B14: Advanced reporting dashboard | C14: 8500 | D14: 20000 | E14: 14000 | F14: No | G14: =IF(F14="Yes",E14,0) | H14: A visual dashboard (Looker Studio) showing marketing performance in near real-time. Once-off build.
B15: CRM workflow setup | C15: 12500 | D15: 35000 | E15: 22500 | F15: No | G15: =IF(F15="Yes",E15,0) | H15: Setting up the CRM so enquiries are captured, assigned to a sales person, and followed up automatically.
B16: Marketing automation setup | C16: 18500 | D16: 55000 | E16: 35000 | F16: No | G16: =IF(F16="Yes",E16,0) | H16: Automated emails, WhatsApps, and status updates triggered by what a lead does or does not do.
B17: Add-ons total included | G17: =SUM(G6:G16) | H17: Only the add-ons switched to Yes are counted. This total flows to Summary.
